stim/__init__.py
stim/__init__.pyi
stim/_detect_machine_architecture.cp312-win_amd64.pyd
stim/_main_argv.py
stim/_stim_polyfill.cp312-win_amd64.pyd
stim/_stim_sse2.cp312-win_amd64.pyd
stim-1.15.0.dist-info/licenses/LICENSE
stim-1.15.0.dist-info/METADATA
stim-1.15.0.dist-info/WHEEL
stim-1.15.0.dist-info/entry_points.txt
stim-1.15.0.dist-info/top_level.txt
stim-1.15.0.dist-info/RECORD
