Metadata-Version: 2.1
Name: stim
Version: 1.15.0
Summary: A fast library for analyzing with quantum stabilizer circuits.
Home-page: https://github.com/quantumlib/stim
Author: Craig Gidney
Author-email: craig.gidney@gmail.com
License: Apache 2
Requires-Python: >=3.6.0
License-File: LICENSE
Requires-Dist: numpy
